[
  {
    "arguments": [
      "/home/keenechen/IMX6ULL/toolchain/gcc-linaro-4.9.4-2017.01-x86_64_arm-linux-gnueabihf/bin/arm-linux-gnueabihf-gcc",
      "-Wall",
      "-std=gnu11",
      "-fno-builtin",
      "-Wa,-mimplicit-it=thumb",
      "-march=armv7-a",
      "-mfpu=neon-vfpv4",
      "-mfloat-abi=hard",
      "-c",
      "-O2",
      "-I",
      "imx6ull",
      "-I",
      "stdio/include",
      "-I",
      "bsp",
      "-I",
      "bsp/clk",
      "-I",
      "bsp/delay",
      "-I",
      "bsp/beep",
      "-I",
      "bsp/led",
      "-I",
      "bsp/gpio",
      "-I",
      "bsp/int",
      "-I",
      "bsp/exti",
      "-I",
      "bsp/epit",
      "-I",
      "bsp/key",
      "-I",
      "bsp/key_filter",
      "-I",
      "bsp/uart",
      "-I",
      "bsp/lcd",
      "-I",
      "bsp/rtc",
      "-I",
      "bsp/i2c",
      "-I",
      "bsp/ap3216c",
      "-I",
      "bsp/spi",
      "-I",
      "bsp/icm20608",
      "-I",
      "bsp/ft5426",
      "-o",
      "obj/start.o",
      "src/start.s"
    ],
    "directory": "/home/keenechen/IMX6ULL/bare_metal_dev/19_touch_screen",
    "file": "/home/keenechen/IMX6ULL/bare_metal_dev/19_touch_screen/src/start.s",
    "output": "/home/keenechen/IMX6ULL/bare_metal_dev/19_touch_screen/obj/start.o"
  },
  {
    "arguments": [
      "/home/keenechen/IMX6ULL/toolchain/gcc-linaro-4.9.4-2017.01-x86_64_arm-linux-gnueabihf/bin/arm-linux-gnueabihf-gcc",
      "-Wall",
      "-std=gnu11",
      "-fno-builtin",
      "-Wa,-mimplicit-it=thumb",
      "-march=armv7-a",
      "-mfpu=neon-vfpv4",
      "-mfloat-abi=hard",
      "-c",
      "-O2",
      "-I",
      "imx6ull",
      "-I",
      "stdio/include",
      "-I",
      "bsp",
      "-I",
      "bsp/clk",
      "-I",
      "bsp/delay",
      "-I",
      "bsp/beep",
      "-I",
      "bsp/led",
      "-I",
      "bsp/gpio",
      "-I",
      "bsp/int",
      "-I",
      "bsp/exti",
      "-I",
      "bsp/epit",
      "-I",
      "bsp/key",
      "-I",
      "bsp/key_filter",
      "-I",
      "bsp/uart",
      "-I",
      "bsp/lcd",
      "-I",
      "bsp/rtc",
      "-I",
      "bsp/i2c",
      "-I",
      "bsp/ap3216c",
      "-I",
      "bsp/spi",
      "-I",
      "bsp/icm20608",
      "-I",
      "bsp/ft5426",
      "-o",
      "obj/main.o",
      "src/main.c"
    ],
    "directory": "/home/keenechen/IMX6ULL/bare_metal_dev/19_touch_screen",
    "file": "/home/keenechen/IMX6ULL/bare_metal_dev/19_touch_screen/src/main.c",
    "output": "/home/keenechen/IMX6ULL/bare_metal_dev/19_touch_screen/obj/main.o"
  },
  {
    "arguments": [
      "/home/keenechen/IMX6ULL/toolchain/gcc-linaro-4.9.4-2017.01-x86_64_arm-linux-gnueabihf/bin/arm-linux-gnueabihf-gcc",
      "-Wall",
      "-std=gnu11",
      "-fno-builtin",
      "-Wa,-mimplicit-it=thumb",
      "-march=armv7-a",
      "-mfpu=neon-vfpv4",
      "-mfloat-abi=hard",
      "-c",
      "-O2",
      "-I",
      "imx6ull",
      "-I",
      "stdio/include",
      "-I",
      "bsp",
      "-I",
      "bsp/clk",
      "-I",
      "bsp/delay",
      "-I",
      "bsp/beep",
      "-I",
      "bsp/led",
      "-I",
      "bsp/gpio",
      "-I",
      "bsp/int",
      "-I",
      "bsp/exti",
      "-I",
      "bsp/epit",
      "-I",
      "bsp/key",
      "-I",
      "bsp/key_filter",
      "-I",
      "bsp/uart",
      "-I",
      "bsp/lcd",
      "-I",
      "bsp/rtc",
      "-I",
      "bsp/i2c",
      "-I",
      "bsp/ap3216c",
      "-I",
      "bsp/spi",
      "-I",
      "bsp/icm20608",
      "-I",
      "bsp/ft5426",
      "-o",
      "obj/ctype.o",
      "stdio/lib/ctype.c"
    ],
    "directory": "/home/keenechen/IMX6ULL/bare_metal_dev/19_touch_screen",
    "file": "/home/keenechen/IMX6ULL/bare_metal_dev/19_touch_screen/stdio/lib/ctype.c",
    "output": "/home/keenechen/IMX6ULL/bare_metal_dev/19_touch_screen/obj/ctype.o"
  },
  {
    "arguments": [
      "/home/keenechen/IMX6ULL/toolchain/gcc-linaro-4.9.4-2017.01-x86_64_arm-linux-gnueabihf/bin/arm-linux-gnueabihf-gcc",
      "-Wall",
      "-std=gnu11",
      "-fno-builtin",
      "-Wa,-mimplicit-it=thumb",
      "-march=armv7-a",
      "-mfpu=neon-vfpv4",
      "-mfloat-abi=hard",
      "-c",
      "-O2",
      "-I",
      "imx6ull",
      "-I",
      "stdio/include",
      "-I",
      "bsp",
      "-I",
      "bsp/clk",
      "-I",
      "bsp/delay",
      "-I",
      "bsp/beep",
      "-I",
      "bsp/led",
      "-I",
      "bsp/gpio",
      "-I",
      "bsp/int",
      "-I",
      "bsp/exti",
      "-I",
      "bsp/epit",
      "-I",
      "bsp/key",
      "-I",
      "bsp/key_filter",
      "-I",
      "bsp/uart",
      "-I",
      "bsp/lcd",
      "-I",
      "bsp/rtc",
      "-I",
      "bsp/i2c",
      "-I",
      "bsp/ap3216c",
      "-I",
      "bsp/spi",
      "-I",
      "bsp/icm20608",
      "-I",
      "bsp/ft5426",
      "-o",
      "obj/div64.o",
      "stdio/lib/div64.c"
    ],
    "directory": "/home/keenechen/IMX6ULL/bare_metal_dev/19_touch_screen",
    "file": "/home/keenechen/IMX6ULL/bare_metal_dev/19_touch_screen/stdio/lib/div64.c",
    "output": "/home/keenechen/IMX6ULL/bare_metal_dev/19_touch_screen/obj/div64.o"
  },
  {
    "arguments": [
      "/home/keenechen/IMX6ULL/toolchain/gcc-linaro-4.9.4-2017.01-x86_64_arm-linux-gnueabihf/bin/arm-linux-gnueabihf-gcc",
      "-Wall",
      "-std=gnu11",
      "-fno-builtin",
      "-Wa,-mimplicit-it=thumb",
      "-march=armv7-a",
      "-mfpu=neon-vfpv4",
      "-mfloat-abi=hard",
      "-c",
      "-O2",
      "-I",
      "imx6ull",
      "-I",
      "stdio/include",
      "-I",
      "bsp",
      "-I",
      "bsp/clk",
      "-I",
      "bsp/delay",
      "-I",
      "bsp/beep",
      "-I",
      "bsp/led",
      "-I",
      "bsp/gpio",
      "-I",
      "bsp/int",
      "-I",
      "bsp/exti",
      "-I",
      "bsp/epit",
      "-I",
      "bsp/key",
      "-I",
      "bsp/key_filter",
      "-I",
      "bsp/uart",
      "-I",
      "bsp/lcd",
      "-I",
      "bsp/rtc",
      "-I",
      "bsp/i2c",
      "-I",
      "bsp/ap3216c",
      "-I",
      "bsp/spi",
      "-I",
      "bsp/icm20608",
      "-I",
      "bsp/ft5426",
      "-o",
      "obj/muldi3.o",
      "stdio/lib/muldi3.c"
    ],
    "directory": "/home/keenechen/IMX6ULL/bare_metal_dev/19_touch_screen",
    "file": "/home/keenechen/IMX6ULL/bare_metal_dev/19_touch_screen/stdio/lib/muldi3.c",
    "output": "/home/keenechen/IMX6ULL/bare_metal_dev/19_touch_screen/obj/muldi3.o"
  },
  {
    "arguments": [
      "/home/keenechen/IMX6ULL/toolchain/gcc-linaro-4.9.4-2017.01-x86_64_arm-linux-gnueabihf/bin/arm-linux-gnueabihf-gcc",
      "-Wall",
      "-std=gnu11",
      "-fno-builtin",
      "-Wa,-mimplicit-it=thumb",
      "-march=armv7-a",
      "-mfpu=neon-vfpv4",
      "-mfloat-abi=hard",
      "-c",
      "-O2",
      "-I",
      "imx6ull",
      "-I",
      "stdio/include",
      "-I",
      "bsp",
      "-I",
      "bsp/clk",
      "-I",
      "bsp/delay",
      "-I",
      "bsp/beep",
      "-I",
      "bsp/led",
      "-I",
      "bsp/gpio",
      "-I",
      "bsp/int",
      "-I",
      "bsp/exti",
      "-I",
      "bsp/epit",
      "-I",
      "bsp/key",
      "-I",
      "bsp/key_filter",
      "-I",
      "bsp/uart",
      "-I",
      "bsp/lcd",
      "-I",
      "bsp/rtc",
      "-I",
      "bsp/i2c",
      "-I",
      "bsp/ap3216c",
      "-I",
      "bsp/spi",
      "-I",
      "bsp/icm20608",
      "-I",
      "bsp/ft5426",
      "-o",
      "obj/printf.o",
      "stdio/lib/printf.c"
    ],
    "directory": "/home/keenechen/IMX6ULL/bare_metal_dev/19_touch_screen",
    "file": "/home/keenechen/IMX6ULL/bare_metal_dev/19_touch_screen/stdio/lib/printf.c",
    "output": "/home/keenechen/IMX6ULL/bare_metal_dev/19_touch_screen/obj/printf.o"
  },
  {
    "arguments": [
      "/home/keenechen/IMX6ULL/toolchain/gcc-linaro-4.9.4-2017.01-x86_64_arm-linux-gnueabihf/bin/arm-linux-gnueabihf-gcc",
      "-Wall",
      "-std=gnu11",
      "-fno-builtin",
      "-Wa,-mimplicit-it=thumb",
      "-march=armv7-a",
      "-mfpu=neon-vfpv4",
      "-mfloat-abi=hard",
      "-c",
      "-O2",
      "-I",
      "imx6ull",
      "-I",
      "stdio/include",
      "-I",
      "bsp",
      "-I",
      "bsp/clk",
      "-I",
      "bsp/delay",
      "-I",
      "bsp/beep",
      "-I",
      "bsp/led",
      "-I",
      "bsp/gpio",
      "-I",
      "bsp/int",
      "-I",
      "bsp/exti",
      "-I",
      "bsp/epit",
      "-I",
      "bsp/key",
      "-I",
      "bsp/key_filter",
      "-I",
      "bsp/uart",
      "-I",
      "bsp/lcd",
      "-I",
      "bsp/rtc",
      "-I",
      "bsp/i2c",
      "-I",
      "bsp/ap3216c",
      "-I",
      "bsp/spi",
      "-I",
      "bsp/icm20608",
      "-I",
      "bsp/ft5426",
      "-o",
      "obj/string.o",
      "stdio/lib/string.c"
    ],
    "directory": "/home/keenechen/IMX6ULL/bare_metal_dev/19_touch_screen",
    "file": "/home/keenechen/IMX6ULL/bare_metal_dev/19_touch_screen/stdio/lib/string.c",
    "output": "/home/keenechen/IMX6ULL/bare_metal_dev/19_touch_screen/obj/string.o"
  },
  {
    "arguments": [
      "/home/keenechen/IMX6ULL/toolchain/gcc-linaro-4.9.4-2017.01-x86_64_arm-linux-gnueabihf/bin/arm-linux-gnueabihf-gcc",
      "-Wall",
      "-std=gnu11",
      "-fno-builtin",
      "-Wa,-mimplicit-it=thumb",
      "-march=armv7-a",
      "-mfpu=neon-vfpv4",
      "-mfloat-abi=hard",
      "-c",
      "-O2",
      "-I",
      "imx6ull",
      "-I",
      "stdio/include",
      "-I",
      "bsp",
      "-I",
      "bsp/clk",
      "-I",
      "bsp/delay",
      "-I",
      "bsp/beep",
      "-I",
      "bsp/led",
      "-I",
      "bsp/gpio",
      "-I",
      "bsp/int",
      "-I",
      "bsp/exti",
      "-I",
      "bsp/epit",
      "-I",
      "bsp/key",
      "-I",
      "bsp/key_filter",
      "-I",
      "bsp/uart",
      "-I",
      "bsp/lcd",
      "-I",
      "bsp/rtc",
      "-I",
      "bsp/i2c",
      "-I",
      "bsp/ap3216c",
      "-I",
      "bsp/spi",
      "-I",
      "bsp/icm20608",
      "-I",
      "bsp/ft5426",
      "-o",
      "obj/vsprintf.o",
      "stdio/lib/vsprintf.c"
    ],
    "directory": "/home/keenechen/IMX6ULL/bare_metal_dev/19_touch_screen",
    "file": "/home/keenechen/IMX6ULL/bare_metal_dev/19_touch_screen/stdio/lib/vsprintf.c",
    "output": "/home/keenechen/IMX6ULL/bare_metal_dev/19_touch_screen/obj/vsprintf.o"
  },
  {
    "arguments": [
      "/home/keenechen/IMX6ULL/toolchain/gcc-linaro-4.9.4-2017.01-x86_64_arm-linux-gnueabihf/bin/arm-linux-gnueabihf-gcc",
      "-Wall",
      "-std=gnu11",
      "-fno-builtin",
      "-Wa,-mimplicit-it=thumb",
      "-march=armv7-a",
      "-mfpu=neon-vfpv4",
      "-mfloat-abi=hard",
      "-c",
      "-O2",
      "-I",
      "imx6ull",
      "-I",
      "stdio/include",
      "-I",
      "bsp",
      "-I",
      "bsp/clk",
      "-I",
      "bsp/delay",
      "-I",
      "bsp/beep",
      "-I",
      "bsp/led",
      "-I",
      "bsp/gpio",
      "-I",
      "bsp/int",
      "-I",
      "bsp/exti",
      "-I",
      "bsp/epit",
      "-I",
      "bsp/key",
      "-I",
      "bsp/key_filter",
      "-I",
      "bsp/uart",
      "-I",
      "bsp/lcd",
      "-I",
      "bsp/rtc",
      "-I",
      "bsp/i2c",
      "-I",
      "bsp/ap3216c",
      "-I",
      "bsp/spi",
      "-I",
      "bsp/icm20608",
      "-I",
      "bsp/ft5426",
      "-o",
      "obj/bsp_clk.o",
      "bsp/clk/bsp_clk.c"
    ],
    "directory": "/home/keenechen/IMX6ULL/bare_metal_dev/19_touch_screen",
    "file": "/home/keenechen/IMX6ULL/bare_metal_dev/19_touch_screen/bsp/clk/bsp_clk.c",
    "output": "/home/keenechen/IMX6ULL/bare_metal_dev/19_touch_screen/obj/bsp_clk.o"
  },
  {
    "arguments": [
      "/home/keenechen/IMX6ULL/toolchain/gcc-linaro-4.9.4-2017.01-x86_64_arm-linux-gnueabihf/bin/arm-linux-gnueabihf-gcc",
      "-Wall",
      "-std=gnu11",
      "-fno-builtin",
      "-Wa,-mimplicit-it=thumb",
      "-march=armv7-a",
      "-mfpu=neon-vfpv4",
      "-mfloat-abi=hard",
      "-c",
      "-O2",
      "-I",
      "imx6ull",
      "-I",
      "stdio/include",
      "-I",
      "bsp",
      "-I",
      "bsp/clk",
      "-I",
      "bsp/delay",
      "-I",
      "bsp/beep",
      "-I",
      "bsp/led",
      "-I",
      "bsp/gpio",
      "-I",
      "bsp/int",
      "-I",
      "bsp/exti",
      "-I",
      "bsp/epit",
      "-I",
      "bsp/key",
      "-I",
      "bsp/key_filter",
      "-I",
      "bsp/uart",
      "-I",
      "bsp/lcd",
      "-I",
      "bsp/rtc",
      "-I",
      "bsp/i2c",
      "-I",
      "bsp/ap3216c",
      "-I",
      "bsp/spi",
      "-I",
      "bsp/icm20608",
      "-I",
      "bsp/ft5426",
      "-o",
      "obj/bsp_beep.o",
      "bsp/beep/bsp_beep.c"
    ],
    "directory": "/home/keenechen/IMX6ULL/bare_metal_dev/19_touch_screen",
    "file": "/home/keenechen/IMX6ULL/bare_metal_dev/19_touch_screen/bsp/beep/bsp_beep.c",
    "output": "/home/keenechen/IMX6ULL/bare_metal_dev/19_touch_screen/obj/bsp_beep.o"
  },
  {
    "arguments": [
      "/home/keenechen/IMX6ULL/toolchain/gcc-linaro-4.9.4-2017.01-x86_64_arm-linux-gnueabihf/bin/arm-linux-gnueabihf-gcc",
      "-Wall",
      "-std=gnu11",
      "-fno-builtin",
      "-Wa,-mimplicit-it=thumb",
      "-march=armv7-a",
      "-mfpu=neon-vfpv4",
      "-mfloat-abi=hard",
      "-c",
      "-O2",
      "-I",
      "imx6ull",
      "-I",
      "stdio/include",
      "-I",
      "bsp",
      "-I",
      "bsp/clk",
      "-I",
      "bsp/delay",
      "-I",
      "bsp/beep",
      "-I",
      "bsp/led",
      "-I",
      "bsp/gpio",
      "-I",
      "bsp/int",
      "-I",
      "bsp/exti",
      "-I",
      "bsp/epit",
      "-I",
      "bsp/key",
      "-I",
      "bsp/key_filter",
      "-I",
      "bsp/uart",
      "-I",
      "bsp/lcd",
      "-I",
      "bsp/rtc",
      "-I",
      "bsp/i2c",
      "-I",
      "bsp/ap3216c",
      "-I",
      "bsp/spi",
      "-I",
      "bsp/icm20608",
      "-I",
      "bsp/ft5426",
      "-o",
      "obj/bsp_delay.o",
      "bsp/delay/bsp_delay.c"
    ],
    "directory": "/home/keenechen/IMX6ULL/bare_metal_dev/19_touch_screen",
    "file": "/home/keenechen/IMX6ULL/bare_metal_dev/19_touch_screen/bsp/delay/bsp_delay.c",
    "output": "/home/keenechen/IMX6ULL/bare_metal_dev/19_touch_screen/obj/bsp_delay.o"
  },
  {
    "arguments": [
      "/home/keenechen/IMX6ULL/toolchain/gcc-linaro-4.9.4-2017.01-x86_64_arm-linux-gnueabihf/bin/arm-linux-gnueabihf-gcc",
      "-Wall",
      "-std=gnu11",
      "-fno-builtin",
      "-Wa,-mimplicit-it=thumb",
      "-march=armv7-a",
      "-mfpu=neon-vfpv4",
      "-mfloat-abi=hard",
      "-c",
      "-O2",
      "-I",
      "imx6ull",
      "-I",
      "stdio/include",
      "-I",
      "bsp",
      "-I",
      "bsp/clk",
      "-I",
      "bsp/delay",
      "-I",
      "bsp/beep",
      "-I",
      "bsp/led",
      "-I",
      "bsp/gpio",
      "-I",
      "bsp/int",
      "-I",
      "bsp/exti",
      "-I",
      "bsp/epit",
      "-I",
      "bsp/key",
      "-I",
      "bsp/key_filter",
      "-I",
      "bsp/uart",
      "-I",
      "bsp/lcd",
      "-I",
      "bsp/rtc",
      "-I",
      "bsp/i2c",
      "-I",
      "bsp/ap3216c",
      "-I",
      "bsp/spi",
      "-I",
      "bsp/icm20608",
      "-I",
      "bsp/ft5426",
      "-o",
      "obj/bsp_led.o",
      "bsp/led/bsp_led.c"
    ],
    "directory": "/home/keenechen/IMX6ULL/bare_metal_dev/19_touch_screen",
    "file": "/home/keenechen/IMX6ULL/bare_metal_dev/19_touch_screen/bsp/led/bsp_led.c",
    "output": "/home/keenechen/IMX6ULL/bare_metal_dev/19_touch_screen/obj/bsp_led.o"
  },
  {
    "arguments": [
      "/home/keenechen/IMX6ULL/toolchain/gcc-linaro-4.9.4-2017.01-x86_64_arm-linux-gnueabihf/bin/arm-linux-gnueabihf-gcc",
      "-Wall",
      "-std=gnu11",
      "-fno-builtin",
      "-Wa,-mimplicit-it=thumb",
      "-march=armv7-a",
      "-mfpu=neon-vfpv4",
      "-mfloat-abi=hard",
      "-c",
      "-O2",
      "-I",
      "imx6ull",
      "-I",
      "stdio/include",
      "-I",
      "bsp",
      "-I",
      "bsp/clk",
      "-I",
      "bsp/delay",
      "-I",
      "bsp/beep",
      "-I",
      "bsp/led",
      "-I",
      "bsp/gpio",
      "-I",
      "bsp/int",
      "-I",
      "bsp/exti",
      "-I",
      "bsp/epit",
      "-I",
      "bsp/key",
      "-I",
      "bsp/key_filter",
      "-I",
      "bsp/uart",
      "-I",
      "bsp/lcd",
      "-I",
      "bsp/rtc",
      "-I",
      "bsp/i2c",
      "-I",
      "bsp/ap3216c",
      "-I",
      "bsp/spi",
      "-I",
      "bsp/icm20608",
      "-I",
      "bsp/ft5426",
      "-o",
      "obj/bsp_gpio.o",
      "bsp/gpio/bsp_gpio.c"
    ],
    "directory": "/home/keenechen/IMX6ULL/bare_metal_dev/19_touch_screen",
    "file": "/home/keenechen/IMX6ULL/bare_metal_dev/19_touch_screen/bsp/gpio/bsp_gpio.c",
    "output": "/home/keenechen/IMX6ULL/bare_metal_dev/19_touch_screen/obj/bsp_gpio.o"
  },
  {
    "arguments": [
      "/home/keenechen/IMX6ULL/toolchain/gcc-linaro-4.9.4-2017.01-x86_64_arm-linux-gnueabihf/bin/arm-linux-gnueabihf-gcc",
      "-Wall",
      "-std=gnu11",
      "-fno-builtin",
      "-Wa,-mimplicit-it=thumb",
      "-march=armv7-a",
      "-mfpu=neon-vfpv4",
      "-mfloat-abi=hard",
      "-c",
      "-O2",
      "-I",
      "imx6ull",
      "-I",
      "stdio/include",
      "-I",
      "bsp",
      "-I",
      "bsp/clk",
      "-I",
      "bsp/delay",
      "-I",
      "bsp/beep",
      "-I",
      "bsp/led",
      "-I",
      "bsp/gpio",
      "-I",
      "bsp/int",
      "-I",
      "bsp/exti",
      "-I",
      "bsp/epit",
      "-I",
      "bsp/key",
      "-I",
      "bsp/key_filter",
      "-I",
      "bsp/uart",
      "-I",
      "bsp/lcd",
      "-I",
      "bsp/rtc",
      "-I",
      "bsp/i2c",
      "-I",
      "bsp/ap3216c",
      "-I",
      "bsp/spi",
      "-I",
      "bsp/icm20608",
      "-I",
      "bsp/ft5426",
      "-o",
      "obj/bsp_int.o",
      "bsp/int/bsp_int.c"
    ],
    "directory": "/home/keenechen/IMX6ULL/bare_metal_dev/19_touch_screen",
    "file": "/home/keenechen/IMX6ULL/bare_metal_dev/19_touch_screen/bsp/int/bsp_int.c",
    "output": "/home/keenechen/IMX6ULL/bare_metal_dev/19_touch_screen/obj/bsp_int.o"
  },
  {
    "arguments": [
      "/home/keenechen/IMX6ULL/toolchain/gcc-linaro-4.9.4-2017.01-x86_64_arm-linux-gnueabihf/bin/arm-linux-gnueabihf-gcc",
      "-Wall",
      "-std=gnu11",
      "-fno-builtin",
      "-Wa,-mimplicit-it=thumb",
      "-march=armv7-a",
      "-mfpu=neon-vfpv4",
      "-mfloat-abi=hard",
      "-c",
      "-O2",
      "-I",
      "imx6ull",
      "-I",
      "stdio/include",
      "-I",
      "bsp",
      "-I",
      "bsp/clk",
      "-I",
      "bsp/delay",
      "-I",
      "bsp/beep",
      "-I",
      "bsp/led",
      "-I",
      "bsp/gpio",
      "-I",
      "bsp/int",
      "-I",
      "bsp/exti",
      "-I",
      "bsp/epit",
      "-I",
      "bsp/key",
      "-I",
      "bsp/key_filter",
      "-I",
      "bsp/uart",
      "-I",
      "bsp/lcd",
      "-I",
      "bsp/rtc",
      "-I",
      "bsp/i2c",
      "-I",
      "bsp/ap3216c",
      "-I",
      "bsp/spi",
      "-I",
      "bsp/icm20608",
      "-I",
      "bsp/ft5426",
      "-o",
      "obj/bsp_exti.o",
      "bsp/exti/bsp_exti.c"
    ],
    "directory": "/home/keenechen/IMX6ULL/bare_metal_dev/19_touch_screen",
    "file": "/home/keenechen/IMX6ULL/bare_metal_dev/19_touch_screen/bsp/exti/bsp_exti.c",
    "output": "/home/keenechen/IMX6ULL/bare_metal_dev/19_touch_screen/obj/bsp_exti.o"
  },
  {
    "arguments": [
      "/home/keenechen/IMX6ULL/toolchain/gcc-linaro-4.9.4-2017.01-x86_64_arm-linux-gnueabihf/bin/arm-linux-gnueabihf-gcc",
      "-Wall",
      "-std=gnu11",
      "-fno-builtin",
      "-Wa,-mimplicit-it=thumb",
      "-march=armv7-a",
      "-mfpu=neon-vfpv4",
      "-mfloat-abi=hard",
      "-c",
      "-O2",
      "-I",
      "imx6ull",
      "-I",
      "stdio/include",
      "-I",
      "bsp",
      "-I",
      "bsp/clk",
      "-I",
      "bsp/delay",
      "-I",
      "bsp/beep",
      "-I",
      "bsp/led",
      "-I",
      "bsp/gpio",
      "-I",
      "bsp/int",
      "-I",
      "bsp/exti",
      "-I",
      "bsp/epit",
      "-I",
      "bsp/key",
      "-I",
      "bsp/key_filter",
      "-I",
      "bsp/uart",
      "-I",
      "bsp/lcd",
      "-I",
      "bsp/rtc",
      "-I",
      "bsp/i2c",
      "-I",
      "bsp/ap3216c",
      "-I",
      "bsp/spi",
      "-I",
      "bsp/icm20608",
      "-I",
      "bsp/ft5426",
      "-o",
      "obj/bsp_epit.o",
      "bsp/epit/bsp_epit.c"
    ],
    "directory": "/home/keenechen/IMX6ULL/bare_metal_dev/19_touch_screen",
    "file": "/home/keenechen/IMX6ULL/bare_metal_dev/19_touch_screen/bsp/epit/bsp_epit.c",
    "output": "/home/keenechen/IMX6ULL/bare_metal_dev/19_touch_screen/obj/bsp_epit.o"
  },
  {
    "arguments": [
      "/home/keenechen/IMX6ULL/toolchain/gcc-linaro-4.9.4-2017.01-x86_64_arm-linux-gnueabihf/bin/arm-linux-gnueabihf-gcc",
      "-Wall",
      "-std=gnu11",
      "-fno-builtin",
      "-Wa,-mimplicit-it=thumb",
      "-march=armv7-a",
      "-mfpu=neon-vfpv4",
      "-mfloat-abi=hard",
      "-c",
      "-O2",
      "-I",
      "imx6ull",
      "-I",
      "stdio/include",
      "-I",
      "bsp",
      "-I",
      "bsp/clk",
      "-I",
      "bsp/delay",
      "-I",
      "bsp/beep",
      "-I",
      "bsp/led",
      "-I",
      "bsp/gpio",
      "-I",
      "bsp/int",
      "-I",
      "bsp/exti",
      "-I",
      "bsp/epit",
      "-I",
      "bsp/key",
      "-I",
      "bsp/key_filter",
      "-I",
      "bsp/uart",
      "-I",
      "bsp/lcd",
      "-I",
      "bsp/rtc",
      "-I",
      "bsp/i2c",
      "-I",
      "bsp/ap3216c",
      "-I",
      "bsp/spi",
      "-I",
      "bsp/icm20608",
      "-I",
      "bsp/ft5426",
      "-o",
      "obj/bsp_key.o",
      "bsp/key/bsp_key.c"
    ],
    "directory": "/home/keenechen/IMX6ULL/bare_metal_dev/19_touch_screen",
    "file": "/home/keenechen/IMX6ULL/bare_metal_dev/19_touch_screen/bsp/key/bsp_key.c",
    "output": "/home/keenechen/IMX6ULL/bare_metal_dev/19_touch_screen/obj/bsp_key.o"
  },
  {
    "arguments": [
      "/home/keenechen/IMX6ULL/toolchain/gcc-linaro-4.9.4-2017.01-x86_64_arm-linux-gnueabihf/bin/arm-linux-gnueabihf-gcc",
      "-Wall",
      "-std=gnu11",
      "-fno-builtin",
      "-Wa,-mimplicit-it=thumb",
      "-march=armv7-a",
      "-mfpu=neon-vfpv4",
      "-mfloat-abi=hard",
      "-c",
      "-O2",
      "-I",
      "imx6ull",
      "-I",
      "stdio/include",
      "-I",
      "bsp",
      "-I",
      "bsp/clk",
      "-I",
      "bsp/delay",
      "-I",
      "bsp/beep",
      "-I",
      "bsp/led",
      "-I",
      "bsp/gpio",
      "-I",
      "bsp/int",
      "-I",
      "bsp/exti",
      "-I",
      "bsp/epit",
      "-I",
      "bsp/key",
      "-I",
      "bsp/key_filter",
      "-I",
      "bsp/uart",
      "-I",
      "bsp/lcd",
      "-I",
      "bsp/rtc",
      "-I",
      "bsp/i2c",
      "-I",
      "bsp/ap3216c",
      "-I",
      "bsp/spi",
      "-I",
      "bsp/icm20608",
      "-I",
      "bsp/ft5426",
      "-o",
      "obj/bsp_key_filter.o",
      "bsp/key_filter/bsp_key_filter.c"
    ],
    "directory": "/home/keenechen/IMX6ULL/bare_metal_dev/19_touch_screen",
    "file": "/home/keenechen/IMX6ULL/bare_metal_dev/19_touch_screen/bsp/key_filter/bsp_key_filter.c",
    "output": "/home/keenechen/IMX6ULL/bare_metal_dev/19_touch_screen/obj/bsp_key_filter.o"
  },
  {
    "arguments": [
      "/home/keenechen/IMX6ULL/toolchain/gcc-linaro-4.9.4-2017.01-x86_64_arm-linux-gnueabihf/bin/arm-linux-gnueabihf-gcc",
      "-Wall",
      "-std=gnu11",
      "-fno-builtin",
      "-Wa,-mimplicit-it=thumb",
      "-march=armv7-a",
      "-mfpu=neon-vfpv4",
      "-mfloat-abi=hard",
      "-c",
      "-O2",
      "-I",
      "imx6ull",
      "-I",
      "stdio/include",
      "-I",
      "bsp",
      "-I",
      "bsp/clk",
      "-I",
      "bsp/delay",
      "-I",
      "bsp/beep",
      "-I",
      "bsp/led",
      "-I",
      "bsp/gpio",
      "-I",
      "bsp/int",
      "-I",
      "bsp/exti",
      "-I",
      "bsp/epit",
      "-I",
      "bsp/key",
      "-I",
      "bsp/key_filter",
      "-I",
      "bsp/uart",
      "-I",
      "bsp/lcd",
      "-I",
      "bsp/rtc",
      "-I",
      "bsp/i2c",
      "-I",
      "bsp/ap3216c",
      "-I",
      "bsp/spi",
      "-I",
      "bsp/icm20608",
      "-I",
      "bsp/ft5426",
      "-o",
      "obj/bsp_uart.o",
      "bsp/uart/bsp_uart.c"
    ],
    "directory": "/home/keenechen/IMX6ULL/bare_metal_dev/19_touch_screen",
    "file": "/home/keenechen/IMX6ULL/bare_metal_dev/19_touch_screen/bsp/uart/bsp_uart.c",
    "output": "/home/keenechen/IMX6ULL/bare_metal_dev/19_touch_screen/obj/bsp_uart.o"
  },
  {
    "arguments": [
      "/home/keenechen/IMX6ULL/toolchain/gcc-linaro-4.9.4-2017.01-x86_64_arm-linux-gnueabihf/bin/arm-linux-gnueabihf-gcc",
      "-Wall",
      "-std=gnu11",
      "-fno-builtin",
      "-Wa,-mimplicit-it=thumb",
      "-march=armv7-a",
      "-mfpu=neon-vfpv4",
      "-mfloat-abi=hard",
      "-c",
      "-O2",
      "-I",
      "imx6ull",
      "-I",
      "stdio/include",
      "-I",
      "bsp",
      "-I",
      "bsp/clk",
      "-I",
      "bsp/delay",
      "-I",
      "bsp/beep",
      "-I",
      "bsp/led",
      "-I",
      "bsp/gpio",
      "-I",
      "bsp/int",
      "-I",
      "bsp/exti",
      "-I",
      "bsp/epit",
      "-I",
      "bsp/key",
      "-I",
      "bsp/key_filter",
      "-I",
      "bsp/uart",
      "-I",
      "bsp/lcd",
      "-I",
      "bsp/rtc",
      "-I",
      "bsp/i2c",
      "-I",
      "bsp/ap3216c",
      "-I",
      "bsp/spi",
      "-I",
      "bsp/icm20608",
      "-I",
      "bsp/ft5426",
      "-o",
      "obj/bsp_lcd_api.o",
      "bsp/lcd/bsp_lcd_api.c"
    ],
    "directory": "/home/keenechen/IMX6ULL/bare_metal_dev/19_touch_screen",
    "file": "/home/keenechen/IMX6ULL/bare_metal_dev/19_touch_screen/bsp/lcd/bsp_lcd_api.c",
    "output": "/home/keenechen/IMX6ULL/bare_metal_dev/19_touch_screen/obj/bsp_lcd_api.o"
  },
  {
    "arguments": [
      "/home/keenechen/IMX6ULL/toolchain/gcc-linaro-4.9.4-2017.01-x86_64_arm-linux-gnueabihf/bin/arm-linux-gnueabihf-gcc",
      "-Wall",
      "-std=gnu11",
      "-fno-builtin",
      "-Wa,-mimplicit-it=thumb",
      "-march=armv7-a",
      "-mfpu=neon-vfpv4",
      "-mfloat-abi=hard",
      "-c",
      "-O2",
      "-I",
      "imx6ull",
      "-I",
      "stdio/include",
      "-I",
      "bsp",
      "-I",
      "bsp/clk",
      "-I",
      "bsp/delay",
      "-I",
      "bsp/beep",
      "-I",
      "bsp/led",
      "-I",
      "bsp/gpio",
      "-I",
      "bsp/int",
      "-I",
      "bsp/exti",
      "-I",
      "bsp/epit",
      "-I",
      "bsp/key",
      "-I",
      "bsp/key_filter",
      "-I",
      "bsp/uart",
      "-I",
      "bsp/lcd",
      "-I",
      "bsp/rtc",
      "-I",
      "bsp/i2c",
      "-I",
      "bsp/ap3216c",
      "-I",
      "bsp/spi",
      "-I",
      "bsp/icm20608",
      "-I",
      "bsp/ft5426",
      "-o",
      "obj/bsp_lcd.o",
      "bsp/lcd/bsp_lcd.c"
    ],
    "directory": "/home/keenechen/IMX6ULL/bare_metal_dev/19_touch_screen",
    "file": "/home/keenechen/IMX6ULL/bare_metal_dev/19_touch_screen/bsp/lcd/bsp_lcd.c",
    "output": "/home/keenechen/IMX6ULL/bare_metal_dev/19_touch_screen/obj/bsp_lcd.o"
  },
  {
    "arguments": [
      "/home/keenechen/IMX6ULL/toolchain/gcc-linaro-4.9.4-2017.01-x86_64_arm-linux-gnueabihf/bin/arm-linux-gnueabihf-gcc",
      "-Wall",
      "-std=gnu11",
      "-fno-builtin",
      "-Wa,-mimplicit-it=thumb",
      "-march=armv7-a",
      "-mfpu=neon-vfpv4",
      "-mfloat-abi=hard",
      "-c",
      "-O2",
      "-I",
      "imx6ull",
      "-I",
      "stdio/include",
      "-I",
      "bsp",
      "-I",
      "bsp/clk",
      "-I",
      "bsp/delay",
      "-I",
      "bsp/beep",
      "-I",
      "bsp/led",
      "-I",
      "bsp/gpio",
      "-I",
      "bsp/int",
      "-I",
      "bsp/exti",
      "-I",
      "bsp/epit",
      "-I",
      "bsp/key",
      "-I",
      "bsp/key_filter",
      "-I",
      "bsp/uart",
      "-I",
      "bsp/lcd",
      "-I",
      "bsp/rtc",
      "-I",
      "bsp/i2c",
      "-I",
      "bsp/ap3216c",
      "-I",
      "bsp/spi",
      "-I",
      "bsp/icm20608",
      "-I",
      "bsp/ft5426",
      "-o",
      "obj/bsp_rtc.o",
      "bsp/rtc/bsp_rtc.c"
    ],
    "directory": "/home/keenechen/IMX6ULL/bare_metal_dev/19_touch_screen",
    "file": "/home/keenechen/IMX6ULL/bare_metal_dev/19_touch_screen/bsp/rtc/bsp_rtc.c",
    "output": "/home/keenechen/IMX6ULL/bare_metal_dev/19_touch_screen/obj/bsp_rtc.o"
  },
  {
    "arguments": [
      "/home/keenechen/IMX6ULL/toolchain/gcc-linaro-4.9.4-2017.01-x86_64_arm-linux-gnueabihf/bin/arm-linux-gnueabihf-gcc",
      "-Wall",
      "-std=gnu11",
      "-fno-builtin",
      "-Wa,-mimplicit-it=thumb",
      "-march=armv7-a",
      "-mfpu=neon-vfpv4",
      "-mfloat-abi=hard",
      "-c",
      "-O2",
      "-I",
      "imx6ull",
      "-I",
      "stdio/include",
      "-I",
      "bsp",
      "-I",
      "bsp/clk",
      "-I",
      "bsp/delay",
      "-I",
      "bsp/beep",
      "-I",
      "bsp/led",
      "-I",
      "bsp/gpio",
      "-I",
      "bsp/int",
      "-I",
      "bsp/exti",
      "-I",
      "bsp/epit",
      "-I",
      "bsp/key",
      "-I",
      "bsp/key_filter",
      "-I",
      "bsp/uart",
      "-I",
      "bsp/lcd",
      "-I",
      "bsp/rtc",
      "-I",
      "bsp/i2c",
      "-I",
      "bsp/ap3216c",
      "-I",
      "bsp/spi",
      "-I",
      "bsp/icm20608",
      "-I",
      "bsp/ft5426",
      "-o",
      "obj/bsp_i2c.o",
      "bsp/i2c/bsp_i2c.c"
    ],
    "directory": "/home/keenechen/IMX6ULL/bare_metal_dev/19_touch_screen",
    "file": "/home/keenechen/IMX6ULL/bare_metal_dev/19_touch_screen/bsp/i2c/bsp_i2c.c",
    "output": "/home/keenechen/IMX6ULL/bare_metal_dev/19_touch_screen/obj/bsp_i2c.o"
  },
  {
    "arguments": [
      "/home/keenechen/IMX6ULL/toolchain/gcc-linaro-4.9.4-2017.01-x86_64_arm-linux-gnueabihf/bin/arm-linux-gnueabihf-gcc",
      "-Wall",
      "-std=gnu11",
      "-fno-builtin",
      "-Wa,-mimplicit-it=thumb",
      "-march=armv7-a",
      "-mfpu=neon-vfpv4",
      "-mfloat-abi=hard",
      "-c",
      "-O2",
      "-I",
      "imx6ull",
      "-I",
      "stdio/include",
      "-I",
      "bsp",
      "-I",
      "bsp/clk",
      "-I",
      "bsp/delay",
      "-I",
      "bsp/beep",
      "-I",
      "bsp/led",
      "-I",
      "bsp/gpio",
      "-I",
      "bsp/int",
      "-I",
      "bsp/exti",
      "-I",
      "bsp/epit",
      "-I",
      "bsp/key",
      "-I",
      "bsp/key_filter",
      "-I",
      "bsp/uart",
      "-I",
      "bsp/lcd",
      "-I",
      "bsp/rtc",
      "-I",
      "bsp/i2c",
      "-I",
      "bsp/ap3216c",
      "-I",
      "bsp/spi",
      "-I",
      "bsp/icm20608",
      "-I",
      "bsp/ft5426",
      "-o",
      "obj/bsp_ap3216c.o",
      "bsp/ap3216c/bsp_ap3216c.c"
    ],
    "directory": "/home/keenechen/IMX6ULL/bare_metal_dev/19_touch_screen",
    "file": "/home/keenechen/IMX6ULL/bare_metal_dev/19_touch_screen/bsp/ap3216c/bsp_ap3216c.c",
    "output": "/home/keenechen/IMX6ULL/bare_metal_dev/19_touch_screen/obj/bsp_ap3216c.o"
  },
  {
    "arguments": [
      "/home/keenechen/IMX6ULL/toolchain/gcc-linaro-4.9.4-2017.01-x86_64_arm-linux-gnueabihf/bin/arm-linux-gnueabihf-gcc",
      "-Wall",
      "-std=gnu11",
      "-fno-builtin",
      "-Wa,-mimplicit-it=thumb",
      "-march=armv7-a",
      "-mfpu=neon-vfpv4",
      "-mfloat-abi=hard",
      "-c",
      "-O2",
      "-I",
      "imx6ull",
      "-I",
      "stdio/include",
      "-I",
      "bsp",
      "-I",
      "bsp/clk",
      "-I",
      "bsp/delay",
      "-I",
      "bsp/beep",
      "-I",
      "bsp/led",
      "-I",
      "bsp/gpio",
      "-I",
      "bsp/int",
      "-I",
      "bsp/exti",
      "-I",
      "bsp/epit",
      "-I",
      "bsp/key",
      "-I",
      "bsp/key_filter",
      "-I",
      "bsp/uart",
      "-I",
      "bsp/lcd",
      "-I",
      "bsp/rtc",
      "-I",
      "bsp/i2c",
      "-I",
      "bsp/ap3216c",
      "-I",
      "bsp/spi",
      "-I",
      "bsp/icm20608",
      "-I",
      "bsp/ft5426",
      "-o",
      "obj/bsp_spi.o",
      "bsp/spi/bsp_spi.c"
    ],
    "directory": "/home/keenechen/IMX6ULL/bare_metal_dev/19_touch_screen",
    "file": "/home/keenechen/IMX6ULL/bare_metal_dev/19_touch_screen/bsp/spi/bsp_spi.c",
    "output": "/home/keenechen/IMX6ULL/bare_metal_dev/19_touch_screen/obj/bsp_spi.o"
  },
  {
    "arguments": [
      "/home/keenechen/IMX6ULL/toolchain/gcc-linaro-4.9.4-2017.01-x86_64_arm-linux-gnueabihf/bin/arm-linux-gnueabihf-gcc",
      "-Wall",
      "-std=gnu11",
      "-fno-builtin",
      "-Wa,-mimplicit-it=thumb",
      "-march=armv7-a",
      "-mfpu=neon-vfpv4",
      "-mfloat-abi=hard",
      "-c",
      "-O2",
      "-I",
      "imx6ull",
      "-I",
      "stdio/include",
      "-I",
      "bsp",
      "-I",
      "bsp/clk",
      "-I",
      "bsp/delay",
      "-I",
      "bsp/beep",
      "-I",
      "bsp/led",
      "-I",
      "bsp/gpio",
      "-I",
      "bsp/int",
      "-I",
      "bsp/exti",
      "-I",
      "bsp/epit",
      "-I",
      "bsp/key",
      "-I",
      "bsp/key_filter",
      "-I",
      "bsp/uart",
      "-I",
      "bsp/lcd",
      "-I",
      "bsp/rtc",
      "-I",
      "bsp/i2c",
      "-I",
      "bsp/ap3216c",
      "-I",
      "bsp/spi",
      "-I",
      "bsp/icm20608",
      "-I",
      "bsp/ft5426",
      "-o",
      "obj/bsp_icm20608.o",
      "bsp/icm20608/bsp_icm20608.c"
    ],
    "directory": "/home/keenechen/IMX6ULL/bare_metal_dev/19_touch_screen",
    "file": "/home/keenechen/IMX6ULL/bare_metal_dev/19_touch_screen/bsp/icm20608/bsp_icm20608.c",
    "output": "/home/keenechen/IMX6ULL/bare_metal_dev/19_touch_screen/obj/bsp_icm20608.o"
  },
  {
    "arguments": [
      "/home/keenechen/IMX6ULL/toolchain/gcc-linaro-4.9.4-2017.01-x86_64_arm-linux-gnueabihf/bin/arm-linux-gnueabihf-gcc",
      "-Wall",
      "-std=gnu11",
      "-fno-builtin",
      "-Wa,-mimplicit-it=thumb",
      "-march=armv7-a",
      "-mfpu=neon-vfpv4",
      "-mfloat-abi=hard",
      "-c",
      "-O2",
      "-I",
      "imx6ull",
      "-I",
      "stdio/include",
      "-I",
      "bsp",
      "-I",
      "bsp/clk",
      "-I",
      "bsp/delay",
      "-I",
      "bsp/beep",
      "-I",
      "bsp/led",
      "-I",
      "bsp/gpio",
      "-I",
      "bsp/int",
      "-I",
      "bsp/exti",
      "-I",
      "bsp/epit",
      "-I",
      "bsp/key",
      "-I",
      "bsp/key_filter",
      "-I",
      "bsp/uart",
      "-I",
      "bsp/lcd",
      "-I",
      "bsp/rtc",
      "-I",
      "bsp/i2c",
      "-I",
      "bsp/ap3216c",
      "-I",
      "bsp/spi",
      "-I",
      "bsp/icm20608",
      "-I",
      "bsp/ft5426",
      "-o",
      "obj/bsp_ft5426.o",
      "bsp/ft5426/bsp_ft5426.c"
    ],
    "directory": "/home/keenechen/IMX6ULL/bare_metal_dev/19_touch_screen",
    "file": "/home/keenechen/IMX6ULL/bare_metal_dev/19_touch_screen/bsp/ft5426/bsp_ft5426.c",
    "output": "/home/keenechen/IMX6ULL/bare_metal_dev/19_touch_screen/obj/bsp_ft5426.o"
  }
]
